zmessage/__init__.py
zmessage/pipeline.py
zmessage/zmessage.py
zmessage/znode.py
zmq_message_patterns-0.1.0.dist-info/LICENSE
zmq_message_patterns-0.1.0.dist-info/METADATA
zmq_message_patterns-0.1.0.dist-info/WHEEL
zmq_message_patterns-0.1.0.dist-info/top_level.txt
zmq_message_patterns-0.1.0.dist-info/RECORD
